CHANGES.md
LICENSE
MANIFEST.in
README.md
setup.cfg
setup.py
src/compman/__init__.py
src/compman/http.py
src/compman/main.py
src/compman/ovshell.py
src/compman/soaringspot.py
src/compman/soarscore.py
src/compman/storage.py
src/compman/xcsoar.py
src/compman/ui/__init__.py
src/compman/ui/activity.py
src/compman/ui/classselector.py
src/compman/ui/compdetails.py
src/compman/ui/mainmenu.py
src/compman/ui/selectcomp.py
src/compman/ui/soaringspot.py
src/compman/ui/taskdownload.py
src/compman/ui/welcome.py
src/compman/ui/widget.py
src/openvario_compman.egg-info/PKG-INFO
src/openvario_compman.egg-info/SOURCES.txt
src/openvario_compman.egg-info/dependency_links.txt
src/openvario_compman.egg-info/entry_points.txt
src/openvario_compman.egg-info/requires.txt
src/openvario_compman.egg-info/top_level.txt
tests/__init__.py
tests/conftest.py
tests/test_main.py
tests/test_ovshell.py
tests/test_soaringspot_real.py
tests/test_soarscore.py
tests/test_storage.py
tests/fixtures/__init__.py
tests/fixtures/activitytestbed.py
tests/fixtures/soaringspot.py
tests/fixtures/soarscore.py
tests/fixtures/widgettestbed.py
tests/fixtures/soarscore/no-tasks.html
tests/fixtures/soarscore/two-classes.html
tests/fixtures/xcsoar/openvario.prf
tests/ui/__init__.py
tests/ui/test_classselector.py
tests/ui/test_compdetails.py
tests/ui/test_mainmenu.py
tests/ui/test_selectcomp.py
tests/ui/test_soaringspot.py
tests/ui/test_taskdownload.py
tests/ui/test_welcome.py