Metadata-Version: 2.1
Name: openvario-compman
Version: 0.6.0
Summary: Competition Manager for OpenVario
Home-page: https://github.com/kedder/openvario-compman
Author: Andrey Lebedev
Author-email: andrey.lebedev@gmail.com
License: UNKNOWN
Keywords: openvario tui competition igc xcsoar
Platform: UNKNOWN
Classifier: Development Status :: 3 - Alpha
Classifier: Intended Audience :: End Users/Desktop
Classifier: License :: OSI Approved :: GNU Lesser General Public License v3 (LGPLv3)
Classifier: Programming Language :: Python :: 3
Classifier: Programming Language :: Python :: 3.7
Classifier: Programming Language :: Python :: 3.8
Requires-Python: >=3.7, <4
Provides-Extra: dev
Provides-Extra: test
